kafka/__init__.py
kafka/client_async.py
kafka/cluster.py
kafka/codec.py
kafka/conn.py
kafka/errors.py
kafka/future.py
kafka/msk.py
kafka/scram.py
kafka/structs.py
kafka/util.py
kafka/version.py
kafka/admin/__init__.py
kafka/admin/acl_resource.py
kafka/admin/client.py
kafka/admin/config_resource.py
kafka/admin/new_partitions.py
kafka/admin/new_topic.py
kafka/consumer/__init__.py
kafka/consumer/fetcher.py
kafka/consumer/group.py
kafka/consumer/subscription_state.py
kafka/coordinator/__init__.py
kafka/coordinator/base.py
kafka/coordinator/consumer.py
kafka/coordinator/heartbeat.py
kafka/coordinator/protocol.py
kafka/coordinator/assignors/__init__.py
kafka/coordinator/assignors/abstract.py
kafka/coordinator/assignors/range.py
kafka/coordinator/assignors/roundrobin.py
kafka/coordinator/assignors/sticky/__init__.py
kafka/coordinator/assignors/sticky/partition_movements.py
kafka/coordinator/assignors/sticky/sorted_set.py
kafka/coordinator/assignors/sticky/sticky_assignor.py
kafka/metrics/__init__.py
kafka/metrics/compound_stat.py
kafka/metrics/dict_reporter.py
kafka/metrics/kafka_metric.py
kafka/metrics/measurable.py
kafka/metrics/measurable_stat.py
kafka/metrics/metric_config.py
kafka/metrics/metric_name.py
kafka/metrics/metrics.py
kafka/metrics/metrics_reporter.py
kafka/metrics/quota.py
kafka/metrics/stat.py
kafka/metrics/stats/__init__.py
kafka/metrics/stats/avg.py
kafka/metrics/stats/count.py
kafka/metrics/stats/histogram.py
kafka/metrics/stats/max_stat.py
kafka/metrics/stats/min_stat.py
kafka/metrics/stats/percentile.py
kafka/metrics/stats/percentiles.py
kafka/metrics/stats/rate.py
kafka/metrics/stats/sampled_stat.py
kafka/metrics/stats/sensor.py
kafka/metrics/stats/total.py
kafka/oauth/__init__.py
kafka/oauth/abstract.py
kafka/partitioner/__init__.py
kafka/partitioner/default.py
kafka/producer/__init__.py
kafka/producer/buffer.py
kafka/producer/future.py
kafka/producer/kafka.py
kafka/producer/record_accumulator.py
kafka/producer/sender.py
kafka/protocol/__init__.py
diaspora_python-2.0.3.dev1.dist-info/LICENSE
diaspora_python-2.0.3.dev1.dist-info/METADATA
diaspora_python-2.0.3.dev1.dist-info/WHEEL
diaspora_python-2.0.3.dev1.dist-info/top_level.txt
diaspora_python-2.0.3.dev1.dist-info/RECORD
