Metadata-Version: 2.1
Name: diaspora-python
Version: 2.0.3.dev1
Summary: Pure Python client for Apache Kafka
Home-page: https://github.com/globus-labs/kafka-python
Author: Dana Powers
Author-email: dana.powers@gmail.com
License: Apache License 2.0
Keywords: apache kafka,kafka
Classifier: Development Status :: 5 - Production/Stable
Classifier: Intended Audience :: Developers
Classifier: License :: OSI Approved :: Apache Software License
Classifier: Programming Language :: Python
Classifier: Programming Language :: Python :: 2
Classifier: Programming Language :: Python :: 2.7
Classifier: Programming Language :: Python :: 3
Classifier: Programming Language :: Python :: 3.4
Classifier: Programming Language :: Python :: 3.5
Classifier: Programming Language :: Python :: 3.6
Classifier: Programming Language :: Python :: 3.7
Classifier: Programming Language :: Python :: 3.8
Classifier: Programming Language :: Python :: 3.9
Classifier: Programming Language :: Python :: 3.10
Classifier: Programming Language :: Python :: 3.11
Classifier: Programming Language :: Python :: 3.12
Classifier: Programming Language :: Python :: Implementation :: CPython
Classifier: Programming Language :: Python :: Implementation :: PyPy
Classifier: Topic :: Software Development :: Libraries :: Python Modules
License-File: LICENSE
Requires-Dist: botocore <2.0.0,>=1.12.0
Provides-Extra: crc32c
Requires-Dist: crc32c ; extra == 'crc32c'
Provides-Extra: lz4
Requires-Dist: lz4 ; extra == 'lz4'
Provides-Extra: snappy
Requires-Dist: python-snappy ; extra == 'snappy'
Provides-Extra: zstd
Requires-Dist: zstandard ; extra == 'zstd'
